umair/__init__.py
umair/details.py
umair-0.0.2.dist-info/LICENSE.txt
umair-0.0.2.dist-info/METADATA
umair-0.0.2.dist-info/WHEEL
umair-0.0.2.dist-info/top_level.txt
umair-0.0.2.dist-info/RECORD
